pyrem/__init__.py
pyrem/host.py
pyrem/task.py
pyrem/utils.py
PyREM-0.2.0.dist-info/LICENSE.txt
PyREM-0.2.0.dist-info/METADATA
PyREM-0.2.0.dist-info/WHEEL
PyREM-0.2.0.dist-info/top_level.txt
PyREM-0.2.0.dist-info/RECORD
