Metadata-Version: 2.1
Name: PyREM
Version: 0.2.0
Summary: Python Remote Experiment Runner
Home-page: https://github.com/emichael/PyREM
Author: Ellis Michael
Author-email: ellis@ellismichael.com
License: MIT
Keywords: remote management,distributed,experiment
Platform: UNKNOWN
Classifier: Development Status :: 2 - Pre-Alpha
Classifier: Intended Audience :: Science/Research
Classifier: Intended Audience :: System Administrators
Classifier: License :: OSI Approved :: MIT License
Classifier: Programming Language :: Python :: 3
Classifier: Topic :: Scientific/Engineering
Classifier: Topic :: Software Development
Classifier: Topic :: System :: Distributed Computing
Requires-Python: >=3.4
Requires-Dist: decorator (<5,>=4.0.2)
